asc/__init__.py
asc/__main__.py
asc/_C/__init__.py
asc/_C/libpyasc.cpython-310-x86_64-linux-gnu.so
asc/codegen/__init__.py
asc/codegen/dependencies_finder.py
asc/codegen/errors.py
asc/codegen/function.py
asc/codegen/function_visitor.py
asc/codegen/name_scope.py
asc/codegen/specialization.py
asc/common/__init__.py
asc/common/compat.py
asc/language/__init__.py
asc/language/adv/__init__.py
asc/language/adv/matmul.py
asc/language/adv/ops.py
asc/language/adv/tiling.py
asc/language/adv/types.py
asc/language/adv/utils.py
asc/language/basic/__init__.py
asc/language/basic/common.py
asc/language/basic/data_copy.py
asc/language/basic/dump_tensor.py
asc/language/basic/sys_var.py
asc/language/basic/utils.py
asc/language/basic/vec_binary.py
asc/language/basic/vec_binary_scalar.py
asc/language/basic/vec_duplicate.py
asc/language/basic/vec_unary.py
asc/language/basic/vec_vconv.py
asc/language/core/__init__.py
asc/language/core/array.py
asc/language/core/constexpr.py
asc/language/core/dtype.py
asc/language/core/enums.py
asc/language/core/ir_value.py
asc/language/core/ops.py
asc/language/core/properties.py
asc/language/core/range.py
asc/language/core/struct.py
asc/language/core/tensor.py
asc/language/core/types.py
asc/language/core/utils.py
asc/language/fwk/__init__.py
asc/language/fwk/tpipe.py
asc/lib/__init__.py
asc/lib/utils.py
asc/lib/host/__init__.py
asc/lib/host/loader.py
asc/lib/host/wrappers.py
asc/lib/host/bindings/Enums.cpp
asc/lib/host/bindings/MatmulApiTiling.cpp
asc/lib/host/bindings/Module.cpp
asc/lib/host/bindings/Platform.cpp
asc/lib/runtime/__init__.py
asc/lib/runtime/build_utils.py
asc/lib/runtime/interface.py
asc/lib/runtime/npu_utils.cpp
asc/lib/runtime/print_utils.cpp
asc/lib/runtime/print_utils.py
asc/lib/runtime/rt_wrapper.cpp
asc/lib/runtime/state.py
asc/lib/runtime/support.py
asc/runtime/__init__.py
asc/runtime/cache.py
asc/runtime/compiler.py
asc/runtime/config.py
asc/runtime/jit.py
asc/runtime/launcher.py
asc/runtime/memory_handle.py
asc/runtime/utils.py
pyasc-1.0.0.dist-info/licenses/LICENSE
pyasc-1.0.0.dist-info/METADATA
pyasc-1.0.0.dist-info/WHEEL
pyasc-1.0.0.dist-info/entry_points.txt
pyasc-1.0.0.dist-info/top_level.txt
pyasc-1.0.0.dist-info/RECORD
