Metadata-Version: 2.4
Name: pyasc
Version: 1.0.0
Summary: Modern programming models for Ascend NPU
License: text = Apache-2.0 WITH LLVM-exception
Classifier: Programming Language :: Python :: 3.8
Classifier: Programming Language :: Python :: 3.9
Classifier: Programming Language :: Python :: 3.10
Classifier: Programming Language :: Python :: 3.11
Classifier: Programming Language :: Python :: 3.12
License-File: LICENSE
Requires-Dist: numpy<2
Requires-Dist: typing_extensions
Provides-Extra: coverage
Requires-Dist: coverage[toml]; extra == "coverage"
Requires-Dist: gcovr; extra == "coverage"
Requires-Dist: pytest-cov; extra == "coverage"
Provides-Extra: dev
Requires-Dist: isort>=6.0.1; extra == "dev"
Requires-Dist: mypy>=1.15.0; extra == "dev"
Requires-Dist: ruff>=0.11.5; extra == "dev"
Requires-Dist: yapf>=0.43.0; extra == "dev"
Provides-Extra: docs
Requires-Dist: myst-parser==4.0.0; extra == "docs"
Requires-Dist: Sphinx==8.1.3; extra == "docs"
Requires-Dist: sphinx-rtd-theme==3.0.2; extra == "docs"
Provides-Extra: test
Requires-Dist: lit; extra == "test"
Requires-Dist: pytest; extra == "test"
Requires-Dist: pytest-xdist; extra == "test"
Dynamic: classifier
Dynamic: license
Dynamic: license-file
Dynamic: provides-extra
Dynamic: requires-dist
Dynamic: summary
